odoo/addons/slow_statement_logger/README.rst
odoo/addons/slow_statement_logger/__init__.py
odoo/addons/slow_statement_logger/__manifest__.py
odoo/addons/slow_statement_logger/i18n/slow_statement_logger.pot
odoo/addons/slow_statement_logger/readme/CONTRIBUTORS.rst
odoo/addons/slow_statement_logger/readme/DESCRIPTION.rst
odoo/addons/slow_statement_logger/readme/USAGE.rst
odoo/addons/slow_statement_logger/static/description/icon.png
odoo/addons/slow_statement_logger/static/description/index.html
odoo12_addon_slow_statement_logger-12.0.1.0.2.dist-info/METADATA
odoo12_addon_slow_statement_logger-12.0.1.0.2.dist-info/WHEEL
odoo12_addon_slow_statement_logger-12.0.1.0.2.dist-info/top_level.txt
odoo12_addon_slow_statement_logger-12.0.1.0.2.dist-info/RECORD
